plprofiler/__init__.py
plprofiler/plprofiler.py
plprofiler/plprofiler_report.py
plprofiler/plprofiler_tool.py
plprofiler/sql_split.py
plprofiler/lib/FlameGraph/README
plprofiler/lib/FlameGraph/README-plprofiler
plprofiler/lib/FlameGraph/flamegraph.pl
plprofiler-4.1.dist-info/DESCRIPTION.rst
plprofiler-4.1.dist-info/METADATA
plprofiler-4.1.dist-info/RECORD
plprofiler-4.1.dist-info/WHEEL
plprofiler-4.1.dist-info/entry_points.txt
plprofiler-4.1.dist-info/metadata.json
plprofiler-4.1.dist-info/top_level.txt
